maamgr/__init__.py
maamgr/core.py
maamgr-0.2.4.dist-info/METADATA
maamgr-0.2.4.dist-info/WHEEL
maamgr-0.2.4.dist-info/entry_points.txt
maamgr-0.2.4.dist-info/licenses/LICENSE
maamgr-0.2.4.dist-info/RECORD
