Metadata-Version: 2.4
Name: maamgr
Version: 0.2.4
Summary: Maa based apps Manager
Author-email: cel-ti <96926560+cel-ti@users.noreply.github.com>
License-File: LICENSE
Requires-Python: >=3.8
Requires-Dist: click>=8.1.8
Requires-Dist: zuu>=7.0.0
